aclient/__init__.py
aclient/api.py
aclient/client.py
aclient/initclient.py
aclient-1.0.7.dist-info/LICENSE
aclient-1.0.7.dist-info/METADATA
aclient-1.0.7.dist-info/WHEEL
aclient-1.0.7.dist-info/top_level.txt
aclient-1.0.7.dist-info/RECORD
