Metadata-Version: 2.1
Name: aclient
Version: 1.0.7
Summary: 发送大量异步请求
Home-page: https://github.com/PengKe-x/AsyncHttpClient
Author: PengKe
Author-email: 925330867@qq.com
Classifier: Programming Language :: Python :: 3
Classifier: License :: OSI Approved :: MIT License
Classifier: Operating System :: OS Independent
Requires-Python: >=3.6
License-File: LICENSE
Requires-Dist: aiohttp
Requires-Dist: yarl
